flask_cache_pylibmc.py
setup.py
Flask_Cache_PyLibMC.egg-info/PKG-INFO
Flask_Cache_PyLibMC.egg-info/SOURCES.txt
Flask_Cache_PyLibMC.egg-info/dependency_links.txt
Flask_Cache_PyLibMC.egg-info/not-zip-safe
Flask_Cache_PyLibMC.egg-info/requires.txt
Flask_Cache_PyLibMC.egg-info/top_level.txt