Metadata-Version: 1.0
Name: Flask-Cache-PyLibMC
Version: 0.1
Summary: PyLibMC cache for Flask-Cache, supports multiple operations
Home-page: https://github.com/radiosilence/flask-cache-pylibmc/
Author: James Cleveland
Author-email: jamescleveland@gmail.com
License: BSD
Platform: any
Classifier: Environment :: Web Environment
Classifier: Intended Audience :: Developers
Classifier: License :: OSI Approved :: BSD License
Classifier: Operating System :: OS Independent
Classifier: Programming Language :: Python
Classifier: Topic :: Internet :: WWW/HTTP :: Dynamic Content
Classifier: Topic :: Software Development :: Libraries :: Python Modules
